elasticmapping
