Metadata-Version: 1.0
Name: ElasticMapping
Version: 1.2
Summary: A simple mappings builder for Elasticsearch
Home-page: http://github.com/Fizzadar/ElasticMapping
Author: Nick Barrett
Author-email: pointlessrambler@gmail.com
License: UNKNOWN
Platform: UNKNOWN
